scamp_analyzer/__init__.py
scamp_analyzer/main.py
scamp_analyzer/prompts.py
scamp_analyzer-2025.12.21135930.dist-info/METADATA
scamp_analyzer-2025.12.21135930.dist-info/WHEEL
scamp_analyzer-2025.12.21135930.dist-info/top_level.txt
scamp_analyzer-2025.12.21135930.dist-info/RECORD
