Metadata-Version: 2.4
Name: scamp-analyzer
Version: 2025.12.21135930
Summary: A new package that analyzes user-provided text descriptions of mischievous or cleverly unconventional behavior (a 'scamp' scenario) and returns a structured assessment. It evaluates the creativity, hu
Author-email: scamp-analyzer <hi@eugene.plus>
License: MIT
Project-URL: Homepage, https://github.com/chigwell/scamp-analyzer
Requires-Python: >=3.9
Requires-Dist: langchain-llm7>=0.0.0
Requires-Dist: llmatch-messages>=0.0.0
Requires-Dist: langchain-core>=0.3.0
